opml2json/__init__.py
opml2json/__main__.py
opml2json/dump.py
opml2json/otoj.py
opml2json-0.1.0.dist-info/METADATA
opml2json-0.1.0.dist-info/WHEEL
opml2json-0.1.0.dist-info/entry_points.txt
opml2json-0.1.0.dist-info/top_level.txt
opml2json-0.1.0.dist-info/RECORD
