Metadata-Version: 2.1
Name: opml2json
Version: 0.1.0
Summary: convert opml to json
Home-page: https://github.com/vishnu012/opml2json
Author: Vishnu
Author-email: vishnu012@pm.me
License: MIT
Platform: UNKNOWN
Classifier: License :: OSI Approved :: MIT License
Classifier: Programming Language :: Python :: 3.7
